airtrackrelay.py
airtrackrelay-1.0.4.dist-info/licenses/LICENSE
airtrackrelay-1.0.4.dist-info/METADATA
airtrackrelay-1.0.4.dist-info/WHEEL
airtrackrelay-1.0.4.dist-info/entry_points.txt
airtrackrelay-1.0.4.dist-info/top_level.txt
airtrackrelay-1.0.4.dist-info/RECORD
