Metadata-Version: 2.4
Name: airtrackrelay
Version: 1.0.4
Summary: UDP GPS Tracker Relay
Author-email: Nathan Fraser <ndf-zz@6-v.org>
License-Expression: MIT
Project-URL: homepage, https://github.com/ndf-zz/airtrackrelay
Keywords: GPS,UDP,tracking
Classifier: Development Status :: 3 - Alpha
Classifier: Topic :: Other/Nonlisted Topic
Classifier: Operating System :: OS Independent
Classifier: Programming Language :: Python :: 3
Requires-Python: >=3.11
License-File: LICENSE
Requires-Dist: metarace
Requires-Dist: pycryptodomex
Dynamic: license-file
